src/controller.sv
module controllerOld (f3, f7, opcode, regWR, memWR, wbCtrl, aluOp, aluS1, aluS2, branchCtrl, memCtrl, doJump, doBranch);
  input logic [2:0] f3;
  input logic [6:0] f7;
  input logic [6:0] opcode;
  output logic regWR, memWR;
  output logic [1:0] wbCtrl;
  output logic [2:0] branchCtrl;
  output logic [2:0] memCtrl;
  output logic aluS1, aluS2, doBranch, doJump;
  output logic [3:0] aluOp;
  
  always_comb
    begin
      regWR = 1'b0;
      aluS1 = 1'b0;
      aluS2 = 1'b0;
      memWR = 1'b0;
      branchCtrl = 3'b011;
      doJump = 1'b0;
      doBranch = 1'b0;
      memCtrl = 3'b000;
      aluOp = 4'b1001;
      wbCtrl = 2'b11;
      case(opcode)
        7'b0110011: begin // R-type
          regWR = 1'b1;
          wbCtrl = 2'b00;
          aluS1 = 1'b0;
          aluS2 = 1'b1;
          case(f3)
            3'b000: aluOp = (f7[5] == 1'b1) ? {1'b1, f3[2:0]} : {1'b0, f3[2:0]}; // SUB/ADD
            3'b101: aluOp = (f7[5] == 1'b1) ? {1'b1, f3[2:0]} : {1'b0, f3[2:0]}; // SRA/SRL
            3'b001, 3'b010, 3'b011, 3'b100, 3'b110, 3'b111: aluOp = (f7 == 7'b0) ? {1'b0, f3[2:0]} : 4'b1001; // ALU operations/Malformed instruction
          endcase
        end
        
        7'b0010011: begin // I-type (IR-type)
          regWR = 1'b1;
          wbCtrl = 2'b00;
          case(f3)
            3'b101: aluOp = (f7[5] == 1'b1) ? {1'b1, f3[2:0]} : {1'b0, f3[2:0]}; // SRAI/SRLI
            3'b000, 3'b001, 3'b010, 3'b011, 3'b100, 3'b110, 3'b111: aluOp = (f7 == 7'b0) ? {1'b0, f3[2:0]} : 4'b1001;
          endcase
        end
        
        7'b0000011: begin // Loads (IL-type)
          regWR = 1'b1;
          aluOp = 4'b0000;
          wbCtrl = 2'b01;
          case(f3)
            3'b000: memCtrl = 3'b000;   // LB
            3'b001: memCtrl = 3'b001;   // LH
            3'b010: memCtrl = 3'b010;   // LW
            3'b100: memCtrl = 3'b011;   // LBU
            3'b101: memCtrl = 3'b100;   // LHU
            default: memCtrl = 3'b000;  // Malformed instruction
          endcase
        end
        
        7'b0100011: begin // S-type
          memWR = 1'b1;
          aluOp = 4'b0000;
          case(f3)
            3'b000: memCtrl = 3'b101;   // SB
            3'b001: memCtrl = 3'b110;   // SH
            3'b010: memCtrl = 3'b111;   // SW
            default: memCtrl = 3'b000;  // Malformed instruction
          endcase          
        end
        
        7'b1100011: begin // B-type
          branchCtrl = f3;
          doBranch = 1'b1;
          aluS1 = 1'b1;
          aluOp = 4'b0000;
        end
        
        7'b0110111: begin // LUI
          regWR = 1'b1;
          wbCtrl = 2'b00;
          aluOp = 4'b0000;
        end
        
        7'b0010111: begin // AUIPC
          regWR = 1'b1;
          aluS1 = 1'b1;
          wbCtrl = 2'b00;
          aluOp = 4'b0000;
        end
        
        7'b1101111: begin // JAL
          regWR = 1'b1;
          aluS1 = 1'b1;
          wbCtrl = 2'b10;
          aluOp = 4'b0000;
          doJump = 1'b1;
        end
        7'b1100111: begin // JALR
          regWR = 1'b1;
          wbCtrl = 2'b10;
          aluOp = 4'b0000;
          doJump = 1'b1;
        end
        default: begin
          regWR = 1'b0;
          memWR = 1'b0;
          wbCtrl = 2'b11;
          aluS1 = 1'b0;
          aluS2 = 1'b0;
          doJump = 1'b0;
          doBranch = 1'b0;
          branchCtrl = 3'b011;
          aluOp = 4'b1001;
          memCtrl = 3'b000;
        end
    endcase
  end
endmodule

testbench/tb_controller.sv
module tb_controller();
  logic [2:0] f3_tb;
  logic [6:0] f7_tb;
  logic [6:0] opcode_tb;
  logic regWR_tb;
  logic memWR_tb;
  logic [1:0] wbCtrl_tb;
  logic [2:0] branchCtrl_tb;
  logic [2:0] memCtrl_tb;
  logic aluS1_tb, aluS2_tb, doBranch_tb, doJump_tb;
  logic [3:0] aluOp_tb;
  
  controllerOld dut (.f3(f3_tb), 
                  .f7(f7_tb), 
                  .opcode(opcode_tb), 
                  .regWR(regWR_tb), 
                  .memWR(memWR_tb), 
                  .wbCtrl(wbCtrl_tb), 
                  .aluOp(aluOp_tb), 
                  .aluS1(aluS1_tb), 
                  .aluS2(aluS2_tb), 
                  .branchCtrl(branchCtrl_tb), 
                  .memCtrl(memCtrl_tb), 
                  .doJump(doJump_tb), 
                  .doBranch(doBranch_tb)
                 );
  
  initial begin
    $dumpfile("dump.vcd");
    $dumpvars(0, tb_controller);
    f7_tb = 7'b0;
    opcode_tb = 7'b0;
    f3_tb = 3'b0;
    #1 opcode_tb = 7'b0110011; // R-type
    f3_tb = 3'b000;
    #1 f7_tb = 7'b0100000;
    #1 f3_tb = 3'b001;
    #1 f7_tb = 7'b0;
    #1 f3_tb = 3'b010;
    #1 f3_tb = 3'b011;
    #1 f3_tb = 3'b100;
    #1 f3_tb = 3'b101;
    #1 f7_tb = 7'b0100000;
    #1 f3_tb = 3'b110;
    #1 f7_tb = 7'b0;
    #1 f3_tb = 3'b111;
    #1 opcode_tb = 7'b0010011; // IR-Type
    f3_tb = 3'b000;
    #1 f7_tb = 7'b0100000;
    #1 f3_tb = 3'b001;
    #1 f7_tb = 7'b0;
    #1 f3_tb = 3'b010;
    #1 f3_tb = 3'b011;
    #1 f3_tb = 3'b100;
    #1 f3_tb = 3'b101;
    #1 f7_tb = 7'b0100000;
    #1 f3_tb = 3'b110;
    #1 f7_tb = 7'b0;
    #1 f3_tb = 3'b111;
    #1 opcode_tb = 7'b0000011; // IL-Type
    f3_tb = 3'b000;
    #1 f3_tb = 3'b001;
    #1 f3_tb = 3'b010;
    #1 f3_tb = 3'b011;
    #1 f3_tb = 3'b100;
    #1 f3_tb = 3'b101;
    #1 f3_tb = 3'b110;
    #1 f3_tb = 3'b111;
    #1 opcode_tb = 7'b0100011; // S-type
    f3_tb = 3'b000;
    #1 f3_tb = 3'b001;
    #1 f3_tb = 3'b010;
    #1 f3_tb = 3'b011;
    #1 f3_tb = 3'b100;
    #1 f3_tb = 3'b101;
    #1 f3_tb = 3'b110;
    #1 f3_tb = 3'b111;
    #1 opcode_tb = 7'b1100011; // B-type
    f3_tb = 3'b000;
    #1 f3_tb = 3'b001;
    #1 f3_tb = 3'b010;
    #1 f3_tb = 3'b011;
    #1 f3_tb = 3'b100;
    #1 f3_tb = 3'b101;
    #1 f3_tb = 3'b110;
    #1 f3_tb = 3'b111;
    #1 opcode_tb = 7'b0110111; // LUI
    f3_tb = 3'b000;
    #1 f3_tb = 3'b001;
    #1 f3_tb = 3'b010;
    #1 f3_tb = 3'b011;
    #1 f3_tb = 3'b100;
    #1 f3_tb = 3'b101;
    #1 f3_tb = 3'b110;
    #1 f3_tb = 3'b111;
    #1 opcode_tb = 7'b0010111; // AUPIC
    f3_tb = 3'b000;
    #1 f3_tb = 3'b001;
    #1 f3_tb = 3'b010;
    #1 f3_tb = 3'b011;
    #1 f3_tb = 3'b100;
    #1 f3_tb = 3'b101;
    #1 f3_tb = 3'b110;
    #1 f3_tb = 3'b111;
    #1 opcode_tb = 7'b1101111; // JAL
    f3_tb = 3'b000;
    #1 f3_tb = 3'b001;
    #1 f3_tb = 3'b010;
    #1 f3_tb = 3'b011;
    #1 f3_tb = 3'b100;
    #1 f3_tb = 3'b101;
    #1 f3_tb = 3'b110;
    #1 f3_tb = 3'b111;
    #1 opcode_tb = 7'b1100111; // JALR
    f3_tb = 3'b000;
    #1 f3_tb = 3'b001;
    #1 f3_tb = 3'b010;
    #1 f3_tb = 3'b011;
    #1 f3_tb = 3'b100;
    #1 f3_tb = 3'b101;
    #1 f3_tb = 3'b110;
    #1 f3_tb = 3'b111;
    #1 opcode_tb = 7'b0011111; // default case
    #1 $finish;
  end
endmodule

Pipeline-4-stage.sim/sim_1/behav/xsim/dump.vcd
$date
   Sat Oct 26 20:06:29 2024
$end
$version
  2019.1
$end
$timescale
  1ps
$end
$scope module tb_controller $end
$var reg 3 ! f3_tb [2:0] $end
$var reg 7 " f7_tb [6:0] $end
$var reg 7 # opcode_tb [6:0] $end
$var reg 1 $ regWR_tb $end
$var reg 1 % memWR_tb $end
$var reg 2 & wbCtrl_tb [1:0] $end
$var reg 3 ' branchCtrl_tb [2:0] $end
$var reg 3 ( memCtrl_tb [2:0] $end
$var reg 1 ) aluS1_tb $end
$var reg 1 * aluS2_tb $end
$var reg 1 + doBranch_tb $end
$var reg 1 , doJump_tb $end
$var reg 4 - aluOp_tb [3:0] $end
$scope module dut $end
$var wire 3 . f3 [2:0] $end
$var wire 7 / f7 [6:0] $end
$var wire 7 0 opcode [6:0] $end
$var reg 1 $ regWR $end
$var reg 1 % memWR $end
$var reg 2 & wbCtrl [1:0] $end
$var reg 3 ' branchCtrl [2:0] $end
$var reg 3 ( memCtrl [2:0] $end
$var reg 1 ) aluS1 $end
$var reg 1 * aluS2 $end
$var reg 1 + doBranch $end
$var reg 1 , doJump $end
$var reg 4 - aluOp [3:0] $end
$upscope $end
$upscope $end
$enddefinitions $end
#0
$dumpvars
b0 !
b0 "
b0 #
0$
0%
b11 &
b0 '
b0 (
0)
0*
0+
0,
b1001 -
b0 .
b0 /
b0 0
$end
#1000
b0 !
b110011 #
1$
b1 &
1)
1*
b0 -
b110011 0
#2000
b100000 "
b1000 -
b100000 /
#3000
b1 !
b1001 -
b1 .
#4000
b0 "
b1 -
b0 /
#5000
b10 !
b10 -
b10 .
#6000
b11 !
b11 -
b11 .
#7000
b100 !
b100 -
b100 .
#8000
b101 !
b101 -
b101 .
#9000
b100000 "
b1101 -
b100000 /
#10000
b110 !
b1001 -
b110 .
#11000
b0 "
b110 -
b0 /
#12000
b111 !
b111 -
b111 .
#13000
b0 !
b10011 #
0*
b0 -
b0 .
b10011 0
#14000
b1 !
b1 -
b1 .
#15000
b10 !
b10 -
b10 .
#16000
b11 !
b11 -
b11 .
#17000
b100 !
b100 -
b100 .
#18000
b101 !
b101 -
b101 .
#19000
b110 !
b110 -
b110 .
#20000
b111 !
b111 -
b111 .
#21000
b0 !
b11 #
b11 &
b1001 -
b0 .
b11 0
#22000
b1 !
b1 (
b1 .
#23000
b10 !
b10 (
b10 .
#24000
b11 !
b0 (
b11 .
#25000
b100 !
b11 (
b100 .
#26000
b101 !
b100 (
b101 .
#27000
b110 !
b0 (
b110 .
#28000
b111 !
b111 .
#29000
b0 !
b100011 #
0$
1%
b101 (
b0 .
b100011 0
#30000
b1 !
b110 (
b1 .
#31000
b10 !
b111 (
b10 .
#32000
b11 !
b0 (
b11 .
#33000
b100 !
b100 .
#34000
b101 !
b101 .
#35000
b110 !
b110 .
#36000
b111 !
b111 .
#37000
b0 !
b1100011 #
0%
0)
1+
b0 .
b1100011 0
#38000
b1 !
b1 '
b1 .
#39000
b10 !
b10 '
b10 .
#40000
b11 !
b11 '
b11 .
#41000
b100 !
b100 '
b100 .
#42000
b101 !
b101 '
b101 .
#43000
b110 !
b110 '
b110 .
#44000
b111 !
b111 '
b111 .
#45000
b0 !
b110111 #
1$
b1 &
b0 '
1)
0+
b0 -
b0 .
b110111 0
#46000
b1 !
b1 .
#47000
b10 !
b10 .
#48000
b11 !
b11 .
#49000
b100 !
b100 .
#50000
b101 !
b101 .
#51000
b110 !
b110 .
#52000
b111 !
b111 .
#53000
b0 !
b10111 #
b10 &
0)
1,
b0 .
b10111 0
#54000
b1 !
b1 .
#55000
b10 !
b10 .
#56000
b11 !
b11 .
#57000
b100 !
b100 .
#58000
b101 !
b101 .
#59000
b110 !
b110 .
#60000
b111 !
b111 .
#61000
b0 !
b1101111 #
b0 .
b1101111 0
#62000
b1 !
b1 .
#63000
b10 !
b10 .
#64000
b11 !
b11 .
#65000
b100 !
b100 .
#66000
b101 !
b101 .
#67000
b110 !
b110 .
#68000
b111 !
b111 .
#69000
b0 !
b10111 #
b0 .
b10111 0
#70000
b1 !
b1 .
#71000
b10 !
b10 .
#72000
b11 !
b11 .
#73000
b100 !
b100 .
#74000
b101 !
b101 .
#75000
b110 !
b110 .
#76000
b111 !
b111 .
